UdicToolKits
