Metadata-Version: 1.0
Name: UdicToolKits
Version: 1.7
Summary: udic dictionary, stopwords, TextPreprocessing module
Home-page: https://github.com/UDICatNCHU/UdicToolKits
Author: ['yaochungfan']
Author-email: yfan@nchu.edu.tw
License: GPL3.0
Keywords: TextPreprocessing,dictionary,stopwords
Platform: UNKNOWN
